LICENSE
MANIFEST.in
README.md
setup.py
pyscf/pbc/prop/__init__.py
pyscf/pbc/prop/efg/__init__.py
pyscf/pbc/prop/efg/rhf.py
pyscf/pbc/prop/efg/test/test_integral.py
pyscf/pbc/prop/polarizability/__init__.py
pyscf/pbc/prop/polarizability/rhf.py
pyscf/pbc/prop/polarizability/rks.py
pyscf/pbc/prop/polarizability/test/test_rhf.py
pyscf/prop/__init__.py
pyscf/prop/efg/__init__.py
pyscf/prop/efg/dhf.py
pyscf/prop/efg/rhf.py
pyscf/prop/efg/uhf.py
pyscf/prop/efg/test/test_dhf.py
pyscf/prop/efg/test/test_integral.py
pyscf/prop/esr/__init__.py
pyscf/prop/esr/uhf.py
pyscf/prop/esr/uks.py
pyscf/prop/freq/__init__.py
pyscf/prop/freq/rhf.py
pyscf/prop/freq/rks.py
pyscf/prop/freq/uhf.py
pyscf/prop/freq/uks.py
pyscf/prop/gtensor/__init__.py
pyscf/prop/gtensor/dhf.py
pyscf/prop/gtensor/uhf.py
pyscf/prop/gtensor/uks.py
pyscf/prop/gtensor/test/test_uhf.py
pyscf/prop/gtensor/test/test_uks.py
pyscf/prop/hfc/__init__.py
pyscf/prop/hfc/dhf.py
pyscf/prop/hfc/uhf.py
pyscf/prop/hfc/uks.py
pyscf/prop/hfc/test/test_uhf.py
pyscf/prop/magnetizability/__init__.py
pyscf/prop/magnetizability/rhf.py
pyscf/prop/magnetizability/rks.py
pyscf/prop/magnetizability/uhf.py
pyscf/prop/magnetizability/uks.py
pyscf/prop/nmr/__init__.py
pyscf/prop/nmr/dhf.py
pyscf/prop/nmr/rhf.py
pyscf/prop/nmr/rks.py
pyscf/prop/nmr/uhf.py
pyscf/prop/nmr/uks.py
pyscf/prop/nmr/test/test_dft_msc.py
pyscf/prop/nmr/test/test_hf_msc.py
pyscf/prop/nsr/__init__.py
pyscf/prop/nsr/rhf.py
pyscf/prop/nsr/rks.py
pyscf/prop/nsr/uhf.py
pyscf/prop/nsr/uks.py
pyscf/prop/nsr/test/test_rhf.py
pyscf/prop/polarizability/__init__.py
pyscf/prop/polarizability/rhf.py
pyscf/prop/polarizability/rks.py
pyscf/prop/polarizability/uhf.py
pyscf/prop/polarizability/uks.py
pyscf/prop/polarizability/test/test_rhf.py
pyscf/prop/rotational_gtensor/__init__.py
pyscf/prop/rotational_gtensor/rhf.py
pyscf/prop/rotational_gtensor/rks.py
pyscf/prop/rotational_gtensor/uhf.py
pyscf/prop/rotational_gtensor/uks.py
pyscf/prop/rotational_gtensor/test/test_rhf.py
pyscf_properties.egg-info/PKG-INFO
pyscf_properties.egg-info/SOURCES.txt
pyscf_properties.egg-info/dependency_links.txt
pyscf_properties.egg-info/requires.txt
pyscf_properties.egg-info/top_level.txt