Metadata-Version: 1.0
Name: pyscf-properties
Version: 0.1.0
Summary: Molecular and crystal electromagnetic properties
Home-page: UNKNOWN
Author: UNKNOWN
Author-email: UNKNOWN
License: UNKNOWN
Platform: UNKNOWN
